Workbook

Sheet BOM
A1: Care Robot: Bill of Materials (USD, estimates)
A2: Blue cells (Qty, Unit price) are inputs: edit them and every total updates. Prices are estimates; see the Summary sheet for assumptions.
A4: # | B4: Subsystem | C4: Component | D4: Specification / notes | E4: Qty | F4: Unit price (USD est.) | G4: Line total (USD) | H4: Tier | I4: Owner (suggested)
A5: 1 | B5: Compute & control | C5: Raspberry Pi 5 (4 GB) | D5: Onboard ROS 2 + YOLO + OpenCV. Skip if you already own a Pi 5 (a Pi 4 4 GB also works, slower). Aug 2026 list price; memory-driven hikes since Dec 2025 | E5: 1 | F5: 110 | G5: =E5*F5 -> 110 | H5: Core | I5: 4 Vision/AI & integration
A6: 2 | B6: Compute & control | C6: Pi 5 active cooler | D6: Needed to avoid throttling under YOLO load | E6: 1 | F6: 6 | G6: =E6*F6 -> 6 | H6: Core | I6: 4 Vision/AI & integration
A7: 3 | B7: Compute & control | C7: microSD card 64 GB (A2, Class 10) | D7: Ubuntu 24.04 + ROS 2 Jazzy | E7: 1 | F7: 10 | G7: =E7*F7 -> 10 | H7: Core | I7: 4 Vision/AI & integration
A8: 4 | B8: Compute & control | C8: ESP32 DevKit (ESP32-WROOM-32, 38-pin) | D8: Low-level controller: motor PID, encoders, sensors, servos. 1 spare | E8: 2 | F8: 8 | G8: =E8*F8 -> 16 | H8: Core | I8: 1 Drive & power
A9: 5 | B9: Compute & control | C9: USB data cable (Pi to ESP32) | D9: Serial link carrying your framed protocol | E9: 1 | F9: 3 | G9: =E9*F9 -> 3 | H9: Core | I9: 1 Drive & power
A10: 6 | B10: Compute & control | C10: Pi 5 bench power supply (5 V / 5 A USB-C) | D10: Desk development only; skip if you own one | E10: 1 | F10: 14 | G10: =E10*F10 -> 14 | H10: Optional | I10: 4 Vision/AI & integration
A11: 7 | B11: Vitals sensing | C11: MAX30102 pulse oximeter / heart-rate module | D11: I2C. 1 spare. Needs a light-shielded finger chamber | E11: 2 | F11: 5 | G11: =E11*F11 -> 10 | H11: Core | I11: 2 Vitals
A12: 8 | B12: Vitals sensing | C12: MLX90614 (GY-906) non-contact IR thermometer | D12: Primary temperature sensor, aimed at forehead. Check the field-of-view variant | E12: 1 | F12: 14 | G12: =E12*F12 -> 14 | H12: Core | I12: 2 Vitals
A13: 9 | B13: Vitals sensing | C13: MAX30205 contact temperature breakout | D13: Cross-check against the IR reading | E13: 1 | F13: 12 | G13: =E13*F13 -> 12 | H13: Core | I13: 2 Vitals
A14: 10 | B14: Navigation & safety sensing | C14: HC-SR04 ultrasonic sensor (3.3 V-compatible version) | D14: Front-left / front-right. Trigger one at a time to avoid crosstalk | E14: 2 | F14: 3 | G14: =E14*F14 -> 6 | H14: Core | I14: 1 Drive & power
A15: 11 | B15: Navigation & safety sensing | C15: VL53L0X time-of-flight sensor | D15: Side / low obstacle. Use XSHUT pins to give each a unique I2C address | E15: 2 | F15: 5 | G15: =E15*F15 -> 10 | H15: Core | I15: 1 Drive & power
A16: 12 | B16: Navigation & safety sensing | C16: MPU6050 IMU | D16: Heading for dead reckoning between markers | E16: 1 | F16: 4 | G16: =E16*F16 -> 4 | H16: Core | I16: 1 Drive & power
... A36: 32 | B36: Power & protection | C36: 12 V relay (30 A) with flyback diode | D36: Opened by the E-stop to cut the motor supply | E36: 1 | F36: 5 | G36: =E36*F36 -> 5 | H36: Core | I36: 1 Drive & power
A37: 33 | B37: Power & protection | C37: Main power switch (rocker, 15 A) | E37: 1 | F37: 3 | G37: =E37*F37 -> 3 | H37: Core | I37: 1 Drive & power
A38: 34 | B38: Power & protection | C38: Inline fuse holder + 10 A blade fuses | D38: Main battery protection | E38: 1 | F38: 4 | G38: =E38*F38 -> 4 | H38: Core | I38: 1 Drive & power
A39: 35 | B39: Power & protection | C39: XT60 connector pair | D39: Battery and motor-supply connections | E39: 2 | F39: 2 | G39: =E39*F39 -> 4 | H39: Core | I39: 1 Drive & power
A40: 36 | B40: Structure & wiring | C40: 3D-printing filament, PETG or PLA (1 kg) | D40: Cabinet, drawers, sensor mount, finger chamber. Assumes printer access | E40: 1 | F40: 20 | G40: =E40*F40 -> 20 | H40: Core | I40: Shared
A41: 37 | B41: Structure & wiring | C41: Base plate, 6 mm MDF or acrylic (~40 x 30 cm) | D41: Chassis base | E41: 1 | F41: 10 | G41: =E41*F41 -> 10 | H41: Core | I41: 1 Drive & power
A42: 38 | B42: Structure & wiring | C42: M3/M4 screws, nuts, standoffs kit | E42: 1 | F42: 12 | G42: =E42*F42 -> 12 | H42: Core | I42: Shared
A43: 39 | B43: Structure & wiring | C43: Wires, Dupont/JST connectors, terminal blocks, heat-shrink, perfboard | E43: 1 | F43: 25 | G43: =E43*F43 -> 25 | H43: Core | I43: Shared
A44: 40 | B44: Structure & wiring | C44: Custom ESP32 carrier PCB (e.g. 5 boards, 2-layer) | D44: Only if you design one. Shipping can exceed the board cost | E44: 1 | F44: 30 | G44: =E44*F44 -> 30 | H44: Optional | I44: Shared
A45: 41 | B45: Validation & demo supplies | C45: Commercial fingertip pulse oximeter (reference) | D45: Validate your MAX30102 readings; report the error | E45: 1 | F45: 15 | G45: =E45*F45 -> 15 | H45: Core | I45: 2 Vitals
A46: 42 | B46: Validation & demo supplies | C46: Commercial digital / IR thermometer (reference) | D46: Validate your temperature readings | E46: 1 | F46: 12 | G46: =E46*F46 -> 12 | H46: Core | I46: 2 Vitals
A47: 43 | B47: Validation & demo supplies | C47: Placeholder 'medication' (vitamins, mints) | D47: Never real drugs in the demo | E47: 1 | F47: 5 | G47: =E47*F47 -> 5 | H47: Core | I47: 3 Drawers
A48: 44 | B48: Validation & demo supplies | C48: Disposable finger covers + alcohol wipes | D48: Hygiene between users | E48: 1 | F48: 8 | G48: =E48*F48 -> 8 | H48: Core | I48: 2 Vitals
A49: 45 | B49: Validation & demo supplies | C49: Printed ArUco markers, QR wristbands, calibration checkerboard | D49: Paper, laminated | E49: 1 | F49: 6 | G49: =E49*F49 -> 6 | H49: Core | I49: 4 Vision/AI & integration
C51: Total, all items | G51: =SUM(G5:G49) -> 659

Sheet Summary
A1: Care Robot BOM: Summary
A3: Local currency code | B3: LOCAL | C3: Edit the yellow cells. Enter your local currency per USD (default 1 = shows USD).
A4: Local currency per 1 USD | B4: 1
A5: Contingency on Core items | B5: 0.15
A7: By subsystem
A8: Subsystem | B8: Core (USD) | C8: Optional (USD) | D8: Total (USD)
A9: Compute & control | B9: =SUMIFS(BOM!$G$5:$G$49,BOM!$B$5:$B$49,$A9,BOM!$H$5:$H$49,"Core") -> 145 | C9: =SUMIFS(BOM!$G$5:$G$49,BOM!$B$5:$B$49,$A9,BOM!$H$5:$H$49,"Optional") -> 14 | D9: =B9+C9 -> 159
A10: Vitals sensing | B10: =SUMIFS(BOM!$G$5:$G$49,BOM!$B$5:$B$49,$A10,BOM!$H$5:$H$49,"Core") -> 36 | C10: =SUMIFS(BOM!$G$5:$G$49,BOM!$B$5:$B$49,$A10,BOM!$H$5:$H$49,"Optional") -> 0 | D10: =B10+C10 -> 36
A11: Navigation & safety sensing | B11: =SUMIFS(BOM!$G$5:$G$49,BOM!$B$5:$B$49,$A11,BOM!$H$5:$H$49,"Core") -> 32 | C11: =SUMIFS(BOM!$G$5:$G$49,BOM!$B$5:$B$49,$A11,BOM!$H$5:$H$49,"Optional") -> 0 | D11: =B11+C11 -> 32
A12: Vision & interaction | B12: =SUMIFS(BOM!$G$5:$G$49,BOM!$B$5:$B$49,$A12,BOM!$H$5:$H$49,"Core") -> 25 | C12: =SUMIFS(BOM!$G$5:$G$49,BOM!$B$5:$B$49,$A12,BOM!$H$5:$H$49,"Optional") -> 81 | D12: =B12+C12 -> 106
A13: Drive & motion | B13: =SUMIFS(BOM!$G$5:$G$49,BOM!$B$5:$B$49,$A13,BOM!$H$5:$H$49,"Core") -> 70 | C13: =SUMIFS(BOM!$G$5:$G$49,BOM!$B$5:$B$49,$A13,BOM!$H$5:$H$49,"Optional") -> 0 | D13: =B13+C13 -> 70
A14: Drawers & dispensing | B14: =SUMIFS(BOM!$G$5:$G$49,BOM!$B$5:$B$49,$A14,BOM!$H$5:$H$49,"Core") -> 14 | C14: =SUMIFS(BOM!$G$5:$G$49,BOM!$B$5:$B$49,$A14,BOM!$H$5:$H$49,"Optional") -> 12 | D14: =B14+C14 -> 26
A15: Power & protection | B15: =SUMIFS(BOM!$G$5:$G$49,BOM!$B$5:$B$49,$A15,BOM!$H$5:$H$49,"Core") -> 87 | C15: =SUMIFS(BOM!$G$5:$G$49,BOM!$B$5:$B$49,$A15,BOM!$H$5:$H$49,"Optional") -> 0 | D15: =B15+C15 -> 87
A16: Structure & wiring | B16: =SUMIFS(BOM!$G$5:$G$49,BOM!$B$5:$B$49,$A16,BOM!$H$5:$H$49,"Core") -> 67 | C16: =SUMIFS(BOM!$G$5:$G$49,BOM!$B$5:$B$49,$A16,BOM!$H$5:$H$49,"Optional") -> 30 | D16: =B16+C16 -> 97
A17: Validation & demo supplies | B17: =SUMIFS(BOM!$G$5:$G$49,BOM!$B$5:$B$49,$A17,BOM!$H$5:$H$49,"Core") -> 46 | C17: =SUMIFS(BOM!$G$5:$G$49,BOM!$B$5:$B$49,$A17,BOM!$H$5:$H$49,"Optional") -> 0 | D17: =B17+C17 -> 46
A18: Total | B18: =SUM(B9:B17) -> 522 | C18: =SUM(C9:C17) -> 137 | D18: =SUM(D9:D17) -> 659
A20: By owner (suggested)
A21: Owner | B21: Core (USD) | C21: Optional (USD) | D21: Total (USD)
A22: 1 Drive & power | B22: =SUMIFS(BOM!$G$5:$G$49,BOM!$I$5:$I$49,$A22,BOM!$H$5:$H$49,"Core") -> 212 | C22: =SUMIFS(BOM!$G$5:$G$49,BOM!$I$5:$I$49,$A22,BOM!$H$5:$H$49,"Optional") -> 0 | D22: =B22+C22 -> 212
A23: 2 Vitals | B23: =SUMIFS(BOM!$G$5:$G$49,BOM!$I$5:$I$49,$A23,BOM!$H$5:$H$49,"Core") -> 71 | C23: =SUMIFS(BOM!$G$5:$G$49,BOM!$I$5:$I$49,$A23,BOM!$H$5:$H$49,"Optional") -> 0 | D23: =B23+C23 -> 71
A24: 3 Drawers | B24: =SUMIFS(BOM!$G$5:$G$49,BOM!$I$5:$I$49,$A24,BOM!$H$5:$H$49,"Core") -> 25 | C24: =SUMIFS(BOM!$G$5:$G$49,BOM!$I$5:$I$49,$A24,BOM!$H$5:$H$49,"Optional") -> 12 | D24: =B24+C24 -> 37
A25: 4 Vision/AI & integration | B25: =SUMIFS(BOM!$G$5:$G$49,BOM!$I$5:$I$49,$A25,BOM!$H$5:$H$49,"Core") -> 157 | C25: =SUMIFS(BOM!$G$5:$G$49,BOM!$I$5:$I$49,$A25,BOM!$H$5:$H$49,"Optional") -> 95 | D25: =B25+C25 -> 252
A26: Shared | B26: =SUMIFS(BOM!$G$5:$G$49,BOM!$I$5:$I$49,$A26,BOM!$H$5:$H$49,"Core") -> 57 | C26: =SUMIFS(BOM!$G$5:$G$49,BOM!$I$5:$I$49,$A26,BOM!$H$5:$H$49,"Optional") -> 30 | D26: =B26+C26 -> 87
A27: Total | B27: =SUM(B22:B26) -> 522 | C27: =SUM(C22:C26) -> 137 | D27: =SUM(D22:D26) -> 659
A29: Budget
A30: Core items (USD) | B30: =B18 -> 522
A31: Contingency (USD) | B31: =B30*$B$5 -> 78.3
A32: Core + contingency (USD) | B32: =B30+B31 -> 600.3
A33: Core + contingency (local currency) | B33: =B32*$B$4 -> 600.3
A34: Everything incl. optional + contingency on core (USD) | B34: =D18+B31 -> 737.3
A36: Assumptions
A37: All prices are rough USD estimates for typical online hobby-electronics retailers, not quotes. Check local vendors before ordering.
A38: Raspberry Pi 5 (4 GB) priced at about $110, the Aug 2026 list price; Pi prices rose repeatedly since Dec 2025 because of memory costs. Source: https://magazinmehatronika.com/en/the-2026-raspberry-pi-pricing-and-buying-guide/
A39: Shipping, import duties, and taxes are NOT included and can add materially depending on where you buy.
A40: Assumes the team already owns basic tools (soldering iron, multimeter, hand tools) and has access to a 3D printer.
A41: Contingency (15%) is a team assumption for spares, wrong parts, and price drift. Edit B5.
A42: Medications in the demo are harmless placeholders. The sensors are hobby-grade, not medical devices.
